flask_sqlalchemy_bind/__init__.py
flask_sqlalchemy_bind/sqlalchemy_bind.py
flask_sqlalchemy_bind-1.0.4.dist-info/METADATA
flask_sqlalchemy_bind-1.0.4.dist-info/WHEEL
flask_sqlalchemy_bind-1.0.4.dist-info/top_level.txt
flask_sqlalchemy_bind-1.0.4.dist-info/RECORD
