Metadata-Version: 2.1
Name: flask-sqlalchemy-bind
Version: 1.0.4
Summary: Minimalistic extension to add support for SQLAlchemy to your Flask app.
Home-page: https://github.com/klfoulk16/flask-sqlalchemy-bind
Author: Kelly Foulk
Author-email: klf16@my.fsu.edu
License: MIT
Platform: UNKNOWN
Classifier: License :: OSI Approved :: MIT License
Classifier: Programming Language :: Python :: 3
Classifier: Programming Language :: Python :: 3.9
